math_external/__init__.py
math_external/math_external.py
mathexternal-0.0.1.dist-info/METADATA
mathexternal-0.0.1.dist-info/WHEEL
mathexternal-0.0.1.dist-info/top_level.txt
mathexternal-0.0.1.dist-info/RECORD
