Metadata-Version: 2.1
Name: mathexternal
Version: 0.0.1
Summary: External functionality for int type
